configyml.py
config_yaml-0.0.2.dist-info/DESCRIPTION.rst
config_yaml-0.0.2.dist-info/METADATA
config_yaml-0.0.2.dist-info/RECORD
config_yaml-0.0.2.dist-info/WHEEL
config_yaml-0.0.2.dist-info/metadata.json
config_yaml-0.0.2.dist-info/top_level.txt
